{"A9dOj+/CR6crrMS49EvLwg==":"mbr-1920x1279.jpg","bjNDgnU5YyRJ9h/0vsLuQg==":"mbr-192x188.jpg","KNNnZQiE0qlz3wJUqEP1kA==":"whatsapp%20image%202018-10-04%20at%2015.11.51-95x82.jpg","Hz0MohLmyAE+GWnKqhHC+A==":"mbr-1920x1280.jpg","ur67e8RyFrA2W9zkpIAo/g==":"mbr-1920x1250.jpg","xQbeJkK9YRAMXCU88Gx0wQ==":"mbr-1920x1074.jpg","Ma3a4njNOsN7HFbf6MZDjA==":"mbr-1-1920x1279.jpg","1NfcZ0Nwn8K+7kGqJ56ZVQ==":"mbr-1-1920x1280.jpg","wmU9nJH6QDcFPwy5jdqc0A==":"mbr-1920x1242.jpg","Lx4WaTCQa2W3E91tKcgwTg==":"mbr-1920x1371.jpg","Gkb7XjeXJkmoM+KlfTpQvA==":"mbr-1920x1357.jpg","j6L2V5nvn3u2onOfH1Le7A==":"mbr-1920x1373.jpg","4x14xsNLL+sr+cIufC/uEg==":"mbr-1920x1271.jpg","ihlkf69UyfSmhSyJ1Jvc6w==":"jumbotron.jpg","+UJ9XyVzde0g5gcFLn11WA==":"mbr-1920x1080.jpg","LiUIORYxGXGMpCM1i0NnEA==":"06.jpg","Ly+mdm63lVz6CqSX2vcU6g==":"background3.jpg","4+DzqXFpj/z2AIwVP9lcYQ==":"background5.jpg","eoYU/aiNC4Ce+rsKshUaWw==":"jumbotron2.jpg","g/1qt9G/oNslcqLxcczJSg==":"mbr-1920x1152.jpg","dwm4EvARDIpq9+70/UQnhA==":"mbr-2-1920x1280.jpg","IqXoFUVQTAeYN1FErMpkzg==":"mbr-3-1920x1280.jpg","3m89295VdyWIWCEsgfAUAw==":"mbr-1920x1277.jpg","Co11RAb3NEzi/RnlBqu7rg==":"mbr-1920x1285.jpg","CWb12lVr4hSaaPp9K3miAg==":"mbr-4-1920x1280.jpg","+tN7dcUmAiIdNXdUv8YdKw==":"mbr-1-1920x1271.jpg","+v6+T+lYEXhY4sArFpj+Og==":"mbr-5-1920x1280.jpg","j8F/M7373Pje7PK4JaE9oQ==":"mbr-1-1920x1152.jpg","4nMlkXc5pNdgIfiojm8zTQ==":"mbr-1200x675.jpg","z0+lk4RFwXpb6CVIfDUTLA==":"mbr-1-1200x675.jpg","LnQr8hTSN31FKjAFr6Ieow==":"mbr-2-1200x675.jpg","K94jtAX3bo4fFQHGAEwMCQ==":"mbr-3-1200x675.jpg","y1fROraTva8lNVYCLha2rQ==":"mbr-1200x704.jpg","TY0JB59NqwVf342AvgXDwg==":"mbr-1200x800.jpg","Y6aIFP0RPBR/EQG6Obqr4g==":"mbr-1200x803.jpg","/xndNwGVCKeOBws5Z1CuFA==":"mbr-1-1200x803.jpg","ZhPIynwMIiao0Gu+XhStLA==":"mbr-4-1200x675.jpg","lck9+y+X79bpICUO9UXaxQ==":"mbr-5-1200x675.jpg","GZHgaTS6YYi/Qf4yhZsxkg==":"mbr-1200x801.jpg","SBLTE5U1Id4YqUKHEbMNHQ==":"mbr-1200x822.jpg","3uHpkHrOI261oxPz8dQvPw==":"mbr-1-1200x822.jpg","C6rAm2XweIL1xFc8SwAvAA==":"mbr-2-1200x822.jpg","rgm4LiZ2itLo7Xndl3E52w==":"mbr-1-1200x800.jpg","sxKBEJbdxGoMZpEDRXxaVA==":"mbr-2-1200x800.jpg","bswS2zUm7Okg8h1x7F4bcw==":"mbr-3-1200x800.jpg","E+DBSAc14SQafPzlnyQ6Dg==":"mbr-4-1200x800.jpg","KZeK6tAppX9i+rya7Ya3tQ==":"mbr-5-1200x800.jpg","tLAPjBueq2Lu7yoahiQNKw==":"mbr-6-1200x800.jpg","KwB9Cx01GRjgZxlyM3ma6g==":"mbr-7-1200x800.jpg","hsuT6U3GVEpocG2ScHBhpQ==":"mbr-8-1200x800.jpg","sfadsZ2OlsZJCuz7y4SVUw==":"mbr-9-1200x800.jpg","3xZ6ReNVW5n9EXLNYbZmhw==":"mbr-720x480.jpg","+rJPO2RnZQLbTv25F8xDwQ==":"mbr-1-720x480.jpg","Q8PFILJWBJtw9pZ7a3PA4g==":"mbr-1200x783.jpg","rjq1PdaIhl+eO3cLG9QmEw==":"mbr-1-1200x783.jpg","m7I3JZ7MegLkK/77Ekw/zw==":"mbr-2-1200x783.jpg","NSt1n4ExiQgdMpvhDVVnGw==":"mbr-3-1200x783.jpg","wYT1kLsWkskctLXCgJwpzQ==":"mbr-1200x798.jpg","yDc7C8O4QK59f9ViXwv9DA==":"mbr-1920x1168.jpg","RVWMqzLfBRVkR+J621M6xQ==":"mbr-10-1200x800.jpg","ugyobdgFk+X8nNC6xvsg6A==":"mbr-1200x706.jpg","NLdwTCOlO5ERVHTPXcnxHA==":"mbr-1-1200x706.jpg","l5vfp3gFGSL3zrH1z7foNg==":"mbr-2-1200x706.jpg","c6708vhEqyXUAb8DlniT3w==":"mbr-1-1200x798.jpg","NBeRvGcH5uJp6ycGjhXatA==":"background4.jpg","D/MJwuutwIhlmcioKCvGqA==":"04.jpg","tqkiZk6HXZl8g23AV/DdZA==":"mbr-11-1200x800.jpg","AnMU8b3xTC73E3Cqnu85rQ==":"mbr-1200x814.jpg"}